autodistill_setfit/__init__.py
autodistill_setfit/model.py
autodistill_setfit-0.1.1.dist-info/METADATA
autodistill_setfit-0.1.1.dist-info/WHEEL
autodistill_setfit-0.1.1.dist-info/top_level.txt
autodistill_setfit-0.1.1.dist-info/RECORD
